Workbook

Sheet Sheet1
A1: Book_ID | B1: Title | C1: Author | D1: Genre | E1: Published_Year | F1: Price | G1: Stock
A2: 1 | B2: Configurable modular throughput | C2: Joseph Crane | D2: Biography | E2: 1949 | F2: 21.34 | G2: 100
A3: 2 | B3: Persevering reciprocal knowledge user | C3: Mario Moore | D3: Fantasy | E3: 1971 | F3: 35.8 | G3: 19
A4: 3 | B4: Streamlined coherent initiative | C4: Derrick Howard | D4: Non-Fiction | E4: 1913 | F4: 15.75 | G4: 27
A5: 4 | B5: Customizable 24hour product | C5: Christopher Andrews | D5: Fiction | E5: 2020 | F5: 43.52 | G5: 8
A6: 5 | B6: Adaptive 5thgeneration encoding | C6: Juan Miller | D6: Fantasy | E6: 1956 | F6: 10.95 | G6: 16
A7: 6 | B7: Advanced encompassing implementation | C7: Bryan Morgan | D7: Biography | E7: 1985 | F7: 6.56 | G7: 2
A8: 7 | B8: Open-architected exuding structure | C8: Jacqueline Young | D8: Romance | E8: 1927 | F8: 43.63 | G8: 95
A9: 8 | B9: Persistent local encoding | C9: Troy Cox | D9: Science Fiction | E9: 2019 | F9: 48.99 | G9: 84
A10: 9 | B10: Optimized interactive challenge | C10: Colin Buckley | D10: Fantasy | E10: 1987 | F10: 14.33 | G10: 70
A11: 10 | B11: Ergonomic national hub | C11: Samantha Ruiz | D11: Mystery | E11: 2015 | F11: 24.63 | G11: 25
A12: 11 | B12: Secured zero tolerance time-frame | C12: Denise Barnes | D12: Fantasy | E12: 1998 | F12: 35.95 | G12: 10
A13: 12 | B13: Polarized optimal array | C13: Destiny Scott | D13: Non-Fiction | E13: 1989 | F13: 27.43 | G13: 63
... A501: 500 | B501: Vision-oriented zero tolerance initiative | C501: David Hatfield | D501: Science Fiction | E501: 1921 | F501: 15.94 | G501: 64

Sheet Sheet2
A1: Customer_ID | B1: Name | C1: Email | D1: Phone | E1: City | F1: Country
A2: 1 | B2: Deborah Griffith | C2: balljoseph@wright-keith.net | D2: 1234567891 | E2: South Craigfort | F2: Denmark
A3: 2 | B3: Crystal Clements | C3: kimberlybennett@curtis.com | D3: 1234567892 | E3: East Derekberg | F3: Nicaragua
A4: 3 | B4: Susan Fuller | C4: beanmichael@burnett-stewart.net | D4: 1234567893 | E4: Austinbury | F4: Equatorial Guinea
A5: 4 | B5: Jamie Ramirez | C5: amandahood@warren.com | D5: 1234567894 | E5: Dianamouth | F5: Slovenia
A6: 5 | B6: Marcus Murphy | C6: connerjohn@yahoo.com | D6: 1234567895 | E6: Smithbury | F6: Guinea-Bissau
A7: 6 | B7: Stephen Vasquez | C7: ricemiguel@yahoo.com | D7: 1234567896 | E7: Hamiltonstad | F7: Rwanda
A8: 7 | B8: Susan Hicks | C8: jeffrey91@yahoo.com | D8: 1234567897 | E8: East Rebecca | F8: Montenegro
A9: 8 | B9: Matthew Johnson | C9: austinkenneth@manning.net | D9: 1234567898 | E9: Kirstenborough | F9: Israel
A10: 9 | B10: Matthew Williams | C10: jeffrey41@diaz.com | D10: 1234567899 | E10: Rebeccafurt | F10: Somalia
A11: 10 | B11: Ronald Osborn | C11: staciekelley@heath.com | D11: 1234567900 | E11: Lake Benjamin | F11: Cameroon
A12: 11 | B12: Thomas Garcia | C12: rmiller@gmail.com | D12: 1234567901 | E12: West Monicabury | F12: Argentina
A13: 12 | B13: Jennifer Murray | C13: wilsonbrittany@hotmail.com | D13: 1234567902 | E13: South Ashleychester | F13: Zimbabwe
... A501: 500 | B501: James York | C501: maydavid@maldonado.org | D501: 1234568390 | E501: Port Angela | F501: Moldova

Sheet Sheet3
A1: Order_ID | B1: Customer_ID | C1: Book_ID | D1: Order_Date | E1: Quantity | F1: Total_Amount
A2: 1 | B2: 84 | C2: 169 | D2: 45072 | E2: 8 | F2: 188.56
A3: 2 | B3: 137 | C3: 301 | D3: 44949 | E3: 10 | F3: 216.6
A4: 3 | B4: 216 | C4: 261 | D4: 45439 | E4: 6 | F4: 85.5
A5: 4 | B5: 433 | C5: 343 | D5: 45255 | E5: 7 | F5: 301.21
A6: 5 | B6: 14 | C6: 431 | D6: 45133 | E6: 7 | F6: 136.36
A7: 6 | B7: 439 | C7: 119 | D7: 45576 | E7: 5 | F7: 249.4
A8: 7 | B8: 195 | C8: 467 | D8: 45222 | E8: 6 | F8: 82.92
A9: 8 | B9: 32 | C9: 159 | D9: 45419 | E9: 4 | F9: 144.84
A10: 9 | B10: 109 | C10: 407 | D10: 45295 | E10: 9 | F10: 379.71
A11: 10 | B11: 94 | C11: 122 | D11: 45482 | E11: 4 | F11: 123
A12: 11 | B12: 131 | C12: 206 | D12: 45215 | E12: 1 | F12: 38.01
A13: 12 | B13: 454 | C13: 3 | D13: 45460 | E13: 2 | F13: 31.5
... A501: 500 | B501: 297 | C501: 137 | D501: 45460 | E501: 5 | F501: 131.65

Sheet Master_Data
A1: Order_ID | B1: Customer_ID | C1: Book_ID | D1: Order_Date | E1: Quantity | F1: Customer_Name | G1: Book_Title | H1: Genre | I1: Price | J1: Total_Amount
A2: 1 | B2: 84 | C2: 169 | D2: 45072 | E2: 8 | F2: =VLOOKUP(B2, Sheet2!A:F, 2, FALSE) -> Gary Blair | G2: =VLOOKUP(C2, Sheet1!A:G, 2, FALSE) -> Networked tertiary approach | H2: =VLOOKUP(C2, Sheet1!A:G, 4, FALSE) -> Biography | I2: =VLOOKUP(C2, Sheet1!A:G, 6, FALSE) -> 23.57 | J2: 188.56
A3: 2 | B3: 137 | C3: 301 | D3: 44949 | E3: 10 | F3: =VLOOKUP(B3, Sheet2!A:F, 2, FALSE) -> Steven Miller | G3: =VLOOKUP(C3, Sheet1!A:G, 2, FALSE) -> Polarized high-level installation | H3: =VLOOKUP(C3, Sheet1!A:G, 4, FALSE) -> Fantasy | I3: =VLOOKUP(C3, Sheet1!A:G, 6, FALSE) -> 21.66 | J3: 216.6
A4: 3 | B4: 216 | C4: 261 | D4: 45439 | E4: 6 | F4: =VLOOKUP(B4, Sheet2!A:F, 2, FALSE) -> Phillip Allen | G4: =VLOOKUP(C4, Sheet1!A:G, 2, FALSE) -> Intuitive content-based toolset | H4: =VLOOKUP(C4, Sheet1!A:G, 4, FALSE) -> Science Fiction | I4: =VLOOKUP(C4, Sheet1!A:G, 6, FALSE) -> 14.25 | J4: 85.5
A5: 4 | B5: 433 | C5: 343 | D5: 45255 | E5: 7 | F5: =VLOOKUP(B5, Sheet2!A:F, 2, FALSE) -> Corey Wells | G5: =VLOOKUP(C5, Sheet1!A:G, 2, FALSE) -> De-engineered grid-enabled secured line | H5: =VLOOKUP(C5, Sheet1!A:G, 4, FALSE) -> Mystery | I5: =VLOOKUP(C5, Sheet1!A:G, 6, FALSE) -> 43.03 | J5: 301.21
A6: 5 | B6: 14 | C6: 431 | D6: 45133 | E6: 7 | F6: =VLOOKUP(B6, Sheet2!A:F, 2, FALSE) -> John Wood | G6: =VLOOKUP(C6, Sheet1!A:G, 2, FALSE) -> Synergized fresh-thinking monitoring | H6: =VLOOKUP(C6, Sheet1!A:G, 4, FALSE) -> Romance | I6: =VLOOKUP(C6, Sheet1!A:G, 6, FALSE) -> 19.48 | J6: 136.36
A7: 6 | B7: 439 | C7: 119 | D7: 45576 | E7: 5 | F7: =VLOOKUP(B7, Sheet2!A:F, 2, FALSE) -> Shane Chang | G7: =VLOOKUP(C7, Sheet1!A:G, 2, FALSE) -> Switchable modular moratorium | H7: =VLOOKUP(C7, Sheet1!A:G, 4, FALSE) -> Romance | I7: =VLOOKUP(C7, Sheet1!A:G, 6, FALSE) -> 49.88 | J7: 249.4
A8: 7 | B8: 195 | C8: 467 | D8: 45222 | E8: 6 | F8: =VLOOKUP(B8, Sheet2!A:F, 2, FALSE) -> Dominique Turner | G8: =VLOOKUP(C8, Sheet1!A:G, 2, FALSE) -> Function-based dedicated frame | H8: =VLOOKUP(C8, Sheet1!A:G, 4, FALSE) -> Romance | I8: =VLOOKUP(C8, Sheet1!A:G, 6, FALSE) -> 13.82 | J8: 82.92
A9: 8 | B9: 32 | C9: 159 | D9: 45419 | E9: 4 | F9: =VLOOKUP(B9, Sheet2!A:F, 2, FALSE) -> Jeffrey Shannon | G9: =VLOOKUP(C9, Sheet1!A:G, 2, FALSE) -> Proactive 5thgeneration middleware | H9: =VLOOKUP(C9, Sheet1!A:G, 4, FALSE) -> Biography | I9: =VLOOKUP(C9, Sheet1!A:G, 6, FALSE) -> 36.21 | J9: 144.84
A10: 9 | B10: 109 | C10: 407 | D10: 45295 | E10: 9 | F10: =VLOOKUP(B10, Sheet2!A:F, 2, FALSE) -> Jacob Kelley | G10: =VLOOKUP(C10, Sheet1!A:G, 2, FALSE) -> Mandatory executive groupware | H10: =VLOOKUP(C10, Sheet1!A:G, 4, FALSE) -> Romance | I10: =VLOOKUP(C10, Sheet1!A:G, 6, FALSE) -> 42.19 | J10: 379.71
A11: 10 | B11: 94 | C11: 122 | D11: 45482 | E11: 4 | F11: =VLOOKUP(B11, Sheet2!A:F, 2, FALSE) -> Mr. David Cox | G11: =VLOOKUP(C11, Sheet1!A:G, 2, FALSE) -> Profound leadingedge capability | H11: =VLOOKUP(C11, Sheet1!A:G, 4, FALSE) -> Mystery | I11: =VLOOKUP(C11, Sheet1!A:G, 6, FALSE) -> 30.75 | J11: 123
A12: 11 | B12: 131 | C12: 206 | D12: 45215 | E12: 1 | F12: =VLOOKUP(B12, Sheet2!A:F, 2, FALSE) -> Peter Smith | G12: =VLOOKUP(C12, Sheet1!A:G, 2, FALSE) -> Digitized executive flexibility | H12: =VLOOKUP(C12, Sheet1!A:G, 4, FALSE) -> Non-Fiction | I12: =VLOOKUP(C12, Sheet1!A:G, 6, FALSE) -> 38.01 | J12: 38.01
A13: 12 | B13: 454 | C13: 3 | D13: 45460 | E13: 2 | F13: =VLOOKUP(B13, Sheet2!A:F, 2, FALSE) -> April Anderson | G13: =VLOOKUP(C13, Sheet1!A:G, 2, FALSE) -> Streamlined coherent initiative | H13: =VLOOKUP(C13, Sheet1!A:G, 4, FALSE) -> Non-Fiction | I13: =VLOOKUP(C13, Sheet1!A:G, 6, FALSE) -> 15.75 | J13: 31.5
... A501: 500 | B501: 297 | C501: 137 | D501: 45460 | E501: 5 | F501: =VLOOKUP(B501, Sheet2!A:F, 2, FALSE) -> Ryan Mendoza | G501: =VLOOKUP(C501, Sheet1!A:G, 2, FALSE) -> Networked contextually-based encryption | H501: =VLOOKUP(C501, Sheet1!A:G, 4, FALSE) -> Biography | I501: =VLOOKUP(C501, Sheet1!A:G, 6, FALSE) -> 26.33 | J501: 131.65

Sheet Sales By Genre
A3: Row Labels | B3: Sum of Total_Amount
A4: Biography | B4: 7870.06
A5: Fantasy | B5: 11238.38
A6: Fiction | B6: 7271.22
A7: Mystery | B7: 12788.45
A8: Non-Fiction | B8: 11603.06
A9: Romance | B9: 13086.98
A10: Science Fiction | B10: 11770.51
A11: Grand Total | B11: 75628.66

Sheet Top Customers
A3: Row Labels | B3: Sum of Total_Amount
A4: Kim Turner | B4: 1398.9
A5: Jonathon Strickland | B5: 1080.95
A6: Carrie Perez | B6: 1052.27
A7: Julie Smith | B7: 991
A8: Pamela Gordon | B8: 986.3
A9: Ashley Perez | B9: 942.62
A10: Anthony Young | B10: 929.19
A11: Robert Clark | B11: 746.65
A12: Justin Spencer | B12: 719.93
A13: Alexander Scott | B13: 682.15
A14: Cynthia Cooper | B14: 667.27
A15: Robert Blair | B15: 633.9
... A310: Grand Total | B310: 75628.66

Sheet Monthly Sales Trend
A3: Row Labels | B3: Sum of Total_Amount
A4: 2022 | B4: 2513.36
A5: Dec | B5: 2513.36
A6: 2023 | B6: 36339.97
A7: Jan | B7: 3561.47
A8: Feb | B8: 2091.98
A9: Mar | B9: 2984.54
A10: Apr | B10: 3373.9
A11: May | B11: 5110.81
A12: Jun | B12: 1943.88
A13: Jul | B13: 3238.44
A14: Aug | B14: 2561.58
A15: Sep | B15: 2488.05
... A32: Grand Total | B32: 75628.66

Sheet Dashboard
